<?xml version="1.0"?>
<CONTRIBUTIONDISCLOSURE>
  <filerType>L</filerType>
  <organizationName>AMERICAN PSYCHOLOGICAL ASSOCIATION</organizationName>
  <lobbyistPrefix>Ms.</lobbyistPrefix>
  <lobbyistFirstName>NINA</lobbyistFirstName>
  <lobbyistMiddleName>GAIL</lobbyistMiddleName>
  <lobbyistLastName>LEVITT</lobbyistLastName>
  <lobbyistSuffix />
  <contactName />
  <senateRegID>3162</senateRegID>
  <houseRegID>30849</houseRegID>
  <reportYear>2013</reportYear>
  <reportType>MM</reportType>
  <amendment>false</amendment>
  <comments>
  </comments>
  <signedDate>6/18/2013 3:19:57 PM</signedDate>
  <certifiedcontent>true</certifiedcontent>
  <noContributions>true</noContributions>
  <pacs>
    <pac>
      <name />
    </pac>
  </pacs>
  <contributions>
    <contribution>
      <type />
      <contributorName />
      <payeeName />
      <recipientName />
      <amount />
      <date />
    </contribution>
  </contributions>
</CONTRIBUTIONDISCLOSURE>