<?xml version="1.0"?>
<CONTRIBUTIONDISCLOSURE>
  <filerType>L</filerType>
  <organizationName>American Defense International, Inc.</organizationName>
  <lobbyistPrefix>Mr.</lobbyistPrefix>
  <lobbyistFirstName>MICHAEL</lobbyistFirstName>
  <lobbyistMiddleName />
  <lobbyistLastName>HERSON</lobbyistLastName>
  <lobbyistSuffix />
  <contactName />
  <senateRegID>2194</senateRegID>
  <houseRegID>32825</houseRegID>
  <reportYear>2013</reportYear>
  <reportType>MM</reportType>
  <amendment>false</amendment>
  <comments>Also registered under Bedrock Strategies, LLC.</comments>
  <signedDate>7/3/2013 11:06:58 AM</signedDate>
  <certifiedcontent>true</certifiedcontent>
  <noContributions>false</noContributions>
  <pacs>
    <pac>
      <name />
    </pac>
  </pacs>
  <contributions>
    <contribution>
      <type />
      <contributorName />
      <payeeName />
      <recipientName />
      <amount />
      <date />
    </contribution>
    <contribution>
      <type>FECA</type>
      <contributorName>Self</contributorName>
      <payeeName>Runyan for Congress</payeeName>
      <recipientName>Jon Runyan</recipientName>
      <amount>500.00</amount>
      <date>3/22/2013</date>
    </contribution>
    <contribution>
      <type>FECA</type>
      <contributorName>Self</contributorName>
      <payeeName>Steve Israel for Congress</payeeName>
      <recipientName>Steve Israel</recipientName>
      <amount>250.00</amount>
      <date>3/22/2013</date>
    </contribution>
    <contribution>
      <type>FECA</type>
      <contributorName>Self</contributorName>
      <payeeName>Collins for Senator</payeeName>
      <recipientName>Susan Collins</recipientName>
      <amount>250.00</amount>
      <date>3/22/2013</date>
    </contribution>
    <contribution>
      <type>FECA</type>
      <contributorName>Self</contributorName>
      <payeeName>Graham for Senate</payeeName>
      <recipientName>Lindsey Graham</recipientName>
      <amount>1,750.00</amount>
      <date>3/22/13</date>
    </contribution>
    <contribution>
      <type>FECA</type>
      <contributorName>Self</contributorName>
      <payeeName>Tim Scott for US Senate</payeeName>
      <recipientName>Tim Scott</recipientName>
      <amount>2,000.00</amount>
      <date>5/23/13</date>
    </contribution>
    <contribution>
      <type>FECA</type>
      <contributorName>Self</contributorName>
      <payeeName>Jeff Denham for Congress</payeeName>
      <recipientName>Jeff Denham</recipientName>
      <amount>500.00</amount>
      <date>05/23/2013</date>
    </contribution>
    <contribution>
      <type>FECA</type>
      <contributorName>Self</contributorName>
      <payeeName>Shuster for Congress</payeeName>
      <recipientName>Bill Shuster</recipientName>
      <amount>1,000.00</amount>
      <date>5/23/13</date>
    </contribution>
    <contribution>
      <type>FECA</type>
      <contributorName>Self</contributorName>
      <payeeName>Conaway for Congress</payeeName>
      <recipientName>Mike Conaway</recipientName>
      <amount>500.00</amount>
      <date>5/23/13</date>
    </contribution>
    <contribution>
      <type>FECA</type>
      <contributorName>Self</contributorName>
      <payeeName>Roskam for Congress</payeeName>
      <recipientName>Peter Roskam</recipientName>
      <amount>500.00</amount>
      <date>5/23/13</date>
    </contribution>
    <contribution>
      <type>FECA</type>
      <contributorName>Self</contributorName>
      <payeeName>Camp for Congress</payeeName>
      <recipientName>Dave Camp</recipientName>
      <amount>1,000.00</amount>
      <date>6/21/13</date>
    </contribution>
    <contribution>
      <type>FECA</type>
      <contributorName>Self</contributorName>
      <payeeName>Kristi for Congress</payeeName>
      <recipientName>Kristi Noem</recipientName>
      <amount>500.00</amount>
      <date>06/25/2013</date>
    </contribution>
    <contribution>
      <type>FECA</type>
      <contributorName>Self</contributorName>
      <payeeName>Bill Owens for Congress</payeeName>
      <recipientName>Bill Owens</recipientName>
      <amount>500.00</amount>
      <date>06/25/2013</date>
    </contribution>
    <contribution>
      <type>FECA</type>
      <contributorName>Self</contributorName>
      <payeeName>Cole for Congress</payeeName>
      <recipientName>Tom Cole</recipientName>
      <amount>500.00</amount>
      <date>6/25/13</date>
    </contribution>
    <contribution>
      <type>FECA</type>
      <contributorName>Self</contributorName>
      <payeeName>National Republican Congressional Committee</payeeName>
      <recipientName>National Republican Congressional Committee</recipientName>
      <amount>15,000.00</amount>
      <date>2/25/2013</date>
    </contribution>
    <contribution>
      <type>FECA</type>
      <contributorName>Self</contributorName>
      <payeeName>21st Century PAC</payeeName>
      <recipientName>Buck McKeon</recipientName>
      <amount>500.00</amount>
      <date>3/22/2013</date>
    </contribution>
    <contribution>
      <type>FECA</type>
      <contributorName>Self</contributorName>
      <payeeName>ImPACt Committee</payeeName>
      <recipientName>Michael Turner</recipientName>
      <amount>500.00</amount>
      <date>6/25/2013</date>
    </contribution>
  </contributions>
</CONTRIBUTIONDISCLOSURE>