<?xml version="1.0"?>
<CONTRIBUTIONDISCLOSURE>
  <filerType>L</filerType>
  <organizationName>NOVO NORDISK INC.</organizationName>
  <lobbyistPrefix>Ms.</lobbyistPrefix>
  <lobbyistFirstName>TRICIA</lobbyistFirstName>
  <lobbyistMiddleName />
  <lobbyistLastName>BROOKS</lobbyistLastName>
  <lobbyistSuffix />
  <contactName />
  <senateRegID>284790</senateRegID>
  <houseRegID>36903</houseRegID>
  <reportYear>2013</reportYear>
  <reportType>MM</reportType>
  <amendment>false</amendment>
  <comments>
  </comments>
  <signedDate>7/2/2013 7:49:52 AM</signedDate>
  <certifiedcontent>true</certifiedcontent>
  <noContributions>true</noContributions>
  <pacs>
    <pac>
      <name />
    </pac>
  </pacs>
  <contributions>
    <contribution>
      <type />
      <contributorName />
      <payeeName />
      <recipientName />
      <amount />
      <date />
    </contribution>
  </contributions>
</CONTRIBUTIONDISCLOSURE>